lexrank/__init__.py
lexrank/settings.py
lexrank/algorithms/__init__.py
lexrank/algorithms/power_method.py
lexrank/algorithms/summarizer.py
lexrank/assets/__init__.py
lexrank/assets/stopwords.json.gz
lexrank/assets/stopwords_raw/__init__.py
lexrank/assets/stopwords_raw/ar.txt
lexrank/assets/stopwords_raw/bg.txt
lexrank/assets/stopwords_raw/bn.txt
lexrank/assets/stopwords_raw/cs.txt
lexrank/assets/stopwords_raw/da.txt
lexrank/assets/stopwords_raw/de.txt
lexrank/assets/stopwords_raw/el.txt
lexrank/assets/stopwords_raw/en.txt
lexrank/assets/stopwords_raw/es.txt
lexrank/assets/stopwords_raw/fa.txt
lexrank/assets/stopwords_raw/fi.txt
lexrank/assets/stopwords_raw/fr.txt
lexrank/assets/stopwords_raw/hi.txt
lexrank/assets/stopwords_raw/hu.txt
lexrank/assets/stopwords_raw/it.txt
lexrank/assets/stopwords_raw/mr.txt
lexrank/assets/stopwords_raw/pl.txt
lexrank/assets/stopwords_raw/pt.txt
lexrank/assets/stopwords_raw/ro.txt
lexrank/assets/stopwords_raw/ru.txt
lexrank/assets/stopwords_raw/sv.txt
lexrank/assets/stopwords_raw/uk.txt
lexrank/mappings/__init__.py
lexrank/mappings/stopwords.py
lexrank/tools/__init__.py
lexrank/tools/assemble_stopwords.py
lexrank/utils/__init__.py
lexrank/utils/package.py
lexrank/utils/text.py
lexrank-0.1.0.dist-info/METADATA
lexrank-0.1.0.dist-info/RECORD
lexrank-0.1.0.dist-info/WHEEL
lexrank-0.1.0.dist-info/entry_points.txt
lexrank-0.1.0.dist-info/top_level.txt
