Metadata-Version: 1.2
Name: lexrank
Version: 0.1.0
Summary: LexRank text summarization
Home-page: https://github.com/wikibusiness/lexrank
Author: Luka Shostenko
Author-email: luka.shostenko@gmail.com
Maintainer: Ocean S.A.
Maintainer-email: support@ocean.io
License: MIT
Download-URL: https://github.com/wikibusiness/lexrank/archive/0.1.0.tar.gz
Keywords: lex,rank,lexrank,algorithm,text,summary,summarization
Platform: UNKNOWN
Requires-Python: >=3.5.0
